siger/__init__.py
siger/import_siger.py
siger/verifica_siger.py
siger/visualiza_obra.py
siger/web_siger.py
siger-0.18.0.dist-info/licenses/LICENSE
siger-0.18.0.dist-info/METADATA
siger-0.18.0.dist-info/WHEEL
siger-0.18.0.dist-info/top_level.txt
siger-0.18.0.dist-info/RECORD
