Metadata-Version: 2.4
Name: siger
Version: 0.18.0
Summary: Automações em Python para auxiliar obtenção de dados do SIGER-CEPEL
Home-page: https://github.com/nkbueno/siger
Author: Nathan Kelvi de Almeida Bueno
Author-email: nathankelvi@gmail.com
License-File: LICENSE
Requires-Dist: pandas
Requires-Dist: numpy
Requires-Dist: requests
Requires-Dist: beautifulsoup4
Requires-Dist: selenium
Requires-Dist: DateTime
Requires-Dist: pywin32
Requires-Dist: xlsxwriter
Dynamic: author
Dynamic: author-email
Dynamic: description
Dynamic: description-content-type
Dynamic: home-page
Dynamic: license-file
Dynamic: requires-dist
Dynamic: summary
